alu_components.v
module mux (
   input [19:0] a,
   input [19:0] b,
   input sel,
   output reg [19:0] c
   
);

   always @(a or b or sel) begin
      if (sel)
      // sel = 1, output b
        c = b; 
      else
      //sel = 0, output a
        c = a; 
    
   end  

endmodule

module not_word (
   input [19:0] a,
   output reg [19:0] c
   
);

   always @(a) begin
    // not operation on a,b
        c = ~a;
    
   end  

endmodule


module and_word (
   input [19:0] a,
   input [19:0] b,
   output reg [19:0] c
   
);

   always @(a or b) begin
    // and operation on a,b
        c = a & b ;
    
   end  

endmodule
module dmux(
   input [19:0] I,
   input [3:0] sel,
   output reg [19:0] o0,
   output reg [19:0] o1,
   output reg [19:0] o2,
   output reg [19:0] o3,
   output reg [19:0] o4,
   output reg [19:0] o5,
   output reg [19:0] o6,
   output reg [19:0] o7,
   output reg [19:0] o8,
   output reg [19:0] o9,
   output reg [19:0] o10,
   output reg [19:0] o11,
   output reg [19:0] o12,
   output reg [19:0] o13,
   output reg [19:0] o14,
   output reg [19:0] o15
);

always @(*) begin
   o0= 0;
   o1= 0;
   o2= 0;
   o3= 0;
   o4= 0;
   o5= 0;
   o6= 0;
   o7= 0;
   o8= 0;
   o9= 0;
   o10= 0;
   o11= 0;
   o12= 0;
   o13= 0;
   o14= 0;
   o15= 0;
   case(sel)
      4'b0000: o0= I;
      4'b0001: o1= I;
      4'b0010: o2= I;
      4'b0011: o3= I;
      4'b0100: o4= I;
      4'b0101: o5= I;
      4'b0110: o6= I;
      4'b0111: o7= I;
      4'b1000: o8= I;
      4'b1001: o9= I;
      4'b1010: o10= I;
      4'b1011: o11= I;
      4'b1100: o12= I;
      4'b1101: o13= I;
      4'b1110: o14= I;
      4'b1111: o15= I;
   endcase
end
endmodule 

module or_word (
   input [19:0] a,
   input [19:0] b,
   output reg [19:0] c
   
);

   always @(a or b) begin
    // or operation on a,b
        c = a | b ;
    
   end  

endmodule

module xor_word(
   input [19:0] a,
   input [19:0] b,
   output reg [19:0] c,
   output reg zero
);

   always @(a or b) begin
        c = a ^ b;
        zero = !(|c);
   end  

endmodule

module shift_left(
    input [19:0] a,
    input [3:0] shift_num,
    output reg [19:0] res
   
);

   always @(a or shift_num) begin
    // perform a basic shift left
        res = a << shift_num; 
    
   end  

endmodule

module shift_right(
    input [19:0] a,
    input [3:0] shift_num,
    output reg [19:0] res
   
);

   always @(a or shift_num) begin
    // perform a basic shift right
        res = a >> shift_num; 
    
   end  

endmodule


module ADDER (

    input [19:0] a,
    input [19:0] b,
    input c_in,
    output reg c_out,
    output reg [19:0] res
   
);

   always @(a or b or c_in) begin
    // add a, b, and carry in
        {c_out,res} = a + b + c_in;
    
   end  

endmodule

module incrementer (
    input [19:0] a,
    output reg [19:0] b
);

    always @(a) begin
        b = a + 1;
    end
    
endmodule

module swap (
   input [19:0] a,
   input [19:0] b,
   output reg [19:0] swap_a,
   output reg [19:0] swap_b
);


   always @(a, b) begin
      swap_a = b;
      swap_b = a;
   end  

endmodule
module sub_word(
   input [19:0] a,
   input [19:0] b,
   output reg [19:0] out
);

always @(a or b) begin
   out = a-b;
end
endmodule

module rotate_left(
   input [19:0] a,
   output reg [19:0] res
);

always @(a) begin
   res = {a[18:0],a[19]};
end

endmodule

module rotate_right(
   input [19:0] a,
   output reg [19:0] res
);

always @(a) begin
   res = {a[0],a[19:1]};
end

endmodule

testbench.v
`include "alu_components.v"

`default_nettype none

module tb_mux;
    // Set inputs and outputs
    reg [19:0] a;
    reg [19:0] b;
    reg  sel;
    wire [19:0] c;

    integer i;
    integer MAX_ITERS = 10;
    integer SEED = 10531;

    // Instantiate the MUX
    mux x0 (
        .a (a),
        .b (b),
        .sel (sel),
        .c (c)
        
    );

    initial begin
        a <= 0;
        b <= 0;

        $dumpfile("testbench.vcd");
        $dumpvars(1,x0);
        $monitor ("a: 0b%0b - b: 0b%0b - sel: 0b%0b - 0: 0b%0b", a, b, sel,c);

        for (i = 0; i < MAX_ITERS; i++) begin
            #10 a <= $urandom(SEED);
                b <= $urandom(SEED);
                sel <= $urandom(SEED) % 2;
        end
    end

endmodule


module tb_dmux;
    // Set inputs and outputs
    reg [19:0] I;
    reg [3:0] sel;
    wire [19:0] o0;
    wire [19:0] o1;
    wire [19:0] o2;
    wire [19:0] o3;
    wire [19:0] o4;
    wire [19:0] o5;
    wire [19:0] o6;
    wire [19:0] o7;
    wire [19:0] o8;
    wire [19:0] o9;
    wire [19:0] o10;
    wire [19:0] o11;
    wire [19:0] o12;
    wire [19:0] o13;
    wire [19:0] o14;
    wire [19:0] o15;
    

    integer i;
    integer MAX_ITERS = 25;
    integer SEED = 10531;

    // Instantiate the dmux
    dmux x0 (
        .I (I),
        .sel (sel),
        .o0 (o0),
        .o1 (o1),
        .o2 (o2),
        .o3 (o3),
        .o4 (o4),
        .o5 (o5),
        .o6 (o6),
        .o7 (o7),
        .o8 (o8),
        .o9 (o9),
        .o10 (o10),
        .o11 (o11),
        .o12 (o12),
        .o13 (o13),
        .o14 (o14),
        .o15 (o15)
    );

    initial begin
        $dumpfile("testbench.vcd");
        $dumpvars(1,x0);
        $monitor ("I: 0b%0b - sel: 0b%0b - o0: 0b%0b - o1: 0b%0b - o2: 0b%0b - o3: 0b%0b - o4: 0b%0b - o5: 0b%0b - o6: 0b%0b - o7: 0b%0b - o8: 0b%0b - o9: 0b%0b - o10: 0b%0b - o11: 0b%0b - o12: 0b%0b - o13: 0b%0b - o14: 0b%0b - o15: 0b%0b", I, sel, o0, o1, o2, o3, o4, o5, o6, o7, o8, o9, o10, o11, o12, o13, o14, o15);

        for (i = 0; i < MAX_ITERS; i++) begin
            #10 I <= $urandom(SEED);
                sel <= $urandom(SEED);  
        end
    end

endmodule

module tb_or_word;
    // Set inputs and outputs
    reg [19:0] a;
    reg [19:0] b;
    wire [19:0] c;

    integer i;
    integer MAX_ITERS = 10;
    integer SEED = 10531;

    // Instantiate the OR
    or_word x0 (
        .a (a),
        .b (b),
        .c (c)
        
    );

    initial begin
        a <= 0;
        b <= 0;

        $dumpfile("testbench.vcd");
        $dumpvars(1,x0);
        $monitor ("a: 0b%0b - b: 0b%0b - c: 0b%0b ", a, b,c);

        for (i = 0; i < MAX_ITERS; i++) begin
            #10 a <= $urandom(SEED);
                b <= $urandom(SEED);
        end
    end

endmodule

module tb_xor;
    // Set inputs and outputs
    reg [19:0] a;
    reg [19:0] b;
    wire [19:0] c;
    wire zero;

    integer i;
    integer MAX_ITERS = 10;
    integer SEED = 10531;

    // Instantiate the XOR
    xor_word x0 (
        .a (a),
        .b (b),
        .c (c),
        .zero (zero)
    );

    initial begin
        a <= 0;
        b <= 0;

        $dumpfile("testbench.vcd");
        $dumpvars(1,x0);
        $monitor ("a: 0b%0b - b: 0b%0b - c: 0b%0b - zero: 0b%0b", a, b, c, zero);

        for (i = 0; i < MAX_ITERS; i++) begin
            #10 a <= $urandom(SEED);
                b <= $urandom(SEED);
        end
    end

endmodule

module tb_shift_left;
    // Set inputs and outputs
    reg [19:0] a;
    reg  [3:0] shift_num;
    wire [19:0] res;

    integer i;
    integer MAX_ITERS = 10;
    integer SEED = 10531;

    // Instantiate the SHIFT LEFT
    shift_left x0 (
        .a (a),
        .shift_num (shift_num),
        .res (res)
        
    );

    initial begin
        a <= 0;
        shift_num <= 0;

        $dumpfile("testbench.vcd");
        $dumpvars(1,x0);
        $monitor ("a: 0b%0b - shift_num: 0b%0b - res: 0b%0b ", a,shift_num,res);
        
        for (i = 0; i < MAX_ITERS; i++) begin
            #10 a <= $urandom(SEED);
                shift_num <= $urandom_range(1,5);
        end
        
    end

endmodule


module tb_shift_right;
    // Set inputs and outputs
    reg [19:0] a;
    reg [3:0] shift_num;
    wire [19:0] res;

    integer i;
    integer MAX_ITERS = 10;
    integer SEED = 10531;

    // Instantiate the lshift
    shift_right x0 (
        .a (a),
        .shift_num (shift_num),
        .res (res)
    );

    initial begin
        $dumpfile("testbench.vcd");
        $dumpvars(1,x0);
        $monitor ("a: 0b%0b - shift_num: 0b%0b - res: 0b%0b", a, shift_num, res);

        for (i = 0; i < MAX_ITERS; i++) begin
            #10 a <= $urandom(SEED);
                shift_num <= $urandom(SEED);
        end
    end

endmodule

module tb_ADDER;
    // Set inputs and outputs
    reg [19:0] a;
    reg [19:0] b;
    reg c_in;
    wire c_out;
    wire [19:0] res;

    integer i;
    integer MAX_ITERS = 10;
    integer SEED = 10531;

    // Instantiate the ADDER
    ADDER x0 (
        .a (a),
        .b (b),
        .c_in (c_in),
        .c_out (c_out),
        .res (res)
    );

    initial begin
        a <= 0;
        b <= 0;
        c_in <= 0;

        $dumpfile("testbench.vcd");
        $dumpvars(1,x0);
        $monitor ("a: 0b%0b - b: 0b%0b - c_in: 0b%0b  - c_out: 0b%0b  - res: 0b%0b ", a, b,c_in,c_out,res);

        for (i = 0; i < MAX_ITERS; i++) begin
            #10 a <= $urandom(SEED);
                b <= $urandom(SEED);
                c_in <= $urandom(SEED);
        end
    end

endmodule


module tb_subtractor;
    // Set inputs and outputs
    reg [19:0] a;
    reg [19:0] b;
    wire [19:0] out;

    integer i;
    integer MAX_ITERS = 10;
    integer SEED = 10531;

    // Instantiate the SUB
    sub_word x0 (
        .a (a),
        .b (b),
        .out (out)
    );

    initial begin
        $dumpfile("testbench.vcd");
        $dumpvars(1,x0);
        $monitor ("a: 0b%0b - b: 0b%0b - out: 0b%0b", a, b, out);

        for (i = 0; i < MAX_ITERS; i++) begin
            #10 a <= $urandom(SEED);
                b <= $urandom(SEED);
        end
    end

endmodule

module tb_rotate_right;
    // Set inputs and outputs
    reg [19:0] a;
    wire [19:0] res;

    integer i;
    integer MAX_ITERS = 10;
    integer SEED = 10531;

    // Instantiate the lshift
    rotate_right x0 (
        .a (a),
        .res (res)
    );

    initial begin
        $dumpfile("testbench.vcd");
        $dumpvars(1,x0);
        $monitor ("a: 0b%0b - res: 0b%0b", a, res);

        for (i = 0; i < MAX_ITERS; i++) begin
            #10 a <= $urandom(SEED);
            
        end
    end

endmodule

module tb_rotate_left;
    // Set inputs and outputs
    reg [19:0] a;
    wire [19:0] res;

    integer i;
    integer MAX_ITERS = 10;
    integer SEED = 10531;

    // Instantiate the lshift
    rotate_left x0 (
        .a (a),
        .res (res)
    );

    initial begin
        $dumpfile("testbench.vcd");
        $dumpvars(1,x0);
        $monitor ("a: 0b%0b - res: 0b%0b", a, res);

        for (i = 0; i < MAX_ITERS; i++) begin
            #10 a <= $urandom(SEED);
        
        end
    end

endmodule

testbench.vcd
$date
	Sun Mar 10 00:22:25 2024
$end
$version
	Icarus Verilog
$end
$timescale
	1s
$end
$scope module tb_ADDER $end
$scope module x0 $end
$var wire 20 ! a [19:0] $end
$var wire 20 " b [19:0] $end
$var wire 1 # c_in $end
$var reg 1 $ c_out $end
$var reg 20 % res [19:0] $end
$upscope $end
$upscope $end
$scope module tb_dmux $end
$scope module x0 $end
$var wire 20 & I [19:0] $end
$var wire 4 ' sel [3:0] $end
$var reg 20 ( o0 [19:0] $end
$var reg 20 ) o1 [19:0] $end
$var reg 20 * o10 [19:0] $end
$var reg 20 + o11 [19:0] $end
$var reg 20 , o12 [19:0] $end
$var reg 20 - o13 [19:0] $end
$var reg 20 . o14 [19:0] $end
$var reg 20 / o15 [19:0] $end
$var reg 20 0 o2 [19:0] $end
$var reg 20 1 o3 [19:0] $end
$var reg 20 2 o4 [19:0] $end
$var reg 20 3 o5 [19:0] $end
$var reg 20 4 o6 [19:0] $end
$var reg 20 5 o7 [19:0] $end
$var reg 20 6 o8 [19:0] $end
$var reg 20 7 o9 [19:0] $end
$upscope $end
$upscope $end
$scope module tb_mux $end
$scope module x0 $end
$var wire 20 8 a [19:0] $end
$var wire 20 9 b [19:0] $end
$var wire 1 : sel $end
$var reg 20 ; c [19:0] $end
$upscope $end
$upscope $end
$scope module tb_or_word $end
$scope module x0 $end
$var wire 20 < a [19:0] $end
$var wire 20 = b [19:0] $end
$var reg 20 > c [19:0] $end
$upscope $end
$upscope $end
$scope module tb_rotate_left $end
$scope module x0 $end
$var wire 20 ? a [19:0] $end
$var reg 20 @ res [19:0] $end
$upscope $end
$upscope $end
$scope module tb_rotate_right $end
$scope module x0 $end
$var wire 20 A a [19:0] $end
$var reg 20 B res [19:0] $end
$upscope $end
$upscope $end
$scope module tb_shift_left $end
$scope module x0 $end
$var wire 20 C a [19:0] $end
$var wire 4 D shift_num [3:0] $end
$var reg 20 E res [19:0] $end
$upscope $end
$upscope $end
$scope module tb_shift_right $end
$scope module x0 $end
$var wire 20 F a [19:0] $end
$var wire 4 G shift_num [3:0] $end
$var reg 20 H res [19:0] $end
$upscope $end
$upscope $end
$scope module tb_subtractor $end
$scope module x0 $end
$var wire 20 I a [19:0] $end
$var wire 20 J b [19:0] $end
$var reg 20 K out [19:0] $end
$upscope $end
$upscope $end
$scope module tb_xor $end
$scope module x0 $end
$var wire 20 L a [19:0] $end
$var wire 20 M b [19:0] $end
$var reg 20 N c [19:0] $end
$var reg 1 O zero $end
$upscope $end
$upscope $end
$enddefinitions $end
$comment Show the parameter values. $end
$dumpall
$end
#0
$dumpvars
1O
b0 N
b0 M
b0 L
bx K
bx J
bx I
bx H
bx G
bx F
b0 E
b0 D
b0 C
bx B
bx A
bx @
bx ?
b0 >
b0 =
b0 <
b0 ;
x:
b0 9
b0 8
bx 7
bx 6
bx 5
bx 4
bx 3
bx 2
bx 1
bx 0
bx /
bx .
bx -
bx ,
bx +
bx *
bx )
bx (
bx '
bx &
b0 %
0$
0#
b0 "
b0 !
$end
#10
0O
b11110111001001000000 N
b1001111001001000000 K
b10101011101001 H
b1010111010010101100 E
b1010101110100101011 B
b1010111010010101101 @
b11111111101001010110 >
b10101011101001010110 ;
b0 /
b0 .
b0 -
b0 ,
b0 +
b0 *
b0 7
b0 6
b0 5
b10101011101001010110 4
b0 3
b0 2
b0 1
b0 0
b0 )
b0 (
1$
b1000001001101100 %
b1011100100000010110 M
b10101011101001010110 L
b1011100100000010110 J
b10101011101001010110 I
b110 G
b10101011101001010110 F
b1 D
b10101011101001010110 C
b10101011101001010110 A
b10101011101001010110 ?
b1011100100000010110 =
b10101011101001010110 <
0:
b1011100100000010110 9
b10101011101001010110 8
b110 '
b10101011101001010110 &
b1011100100000010110 "
b10101011101001010110 !
#20
b1100000010111110000 N
b11111110110010000 K
b1100001110 H
b10010000001011000000 E
b101110010000001011 B
b10111001000000101100 @
b11100011110111111010 >
b10100011110000111010 ;
b11000011100111001010 *
b0 4
b1000100001001001110 %
b10100011110000111010 M
b11000011100111001010 L
b10100011110000111010 J
b11000011100111001010 I
b1010 G
b11000011100111001010 F
b101 D
b1011100100000010110 C
b1011100100000010110 A
b1011100100000010110 ?
b10100011110000111010 =
b11000011100111001010 <
b10100000011000010100 9
b10100011110000111010 8
b1010 '
b11000011100111001010 &
b10100000011000010100 "
b10100011110000111010 !
#30
b10111011101100100000 N
b10000100100011100000 K
b1010000001100001 H
b10000111001110010100 E
b1100001110011100101 B
b10000111001110010101 @
b10111011111100110100 >
b11101101111011001 ;
b10100000011000010100 2
b0 *
0$
b11000101010100001010 %
b11011110100110100 M
b10100000011000010100 L
b11011110100110100 J
b10100000011000010100 I
b100 G
b10100000011000010100 F
b1 D
b11000011100111001010 C
b11000011100111001010 A
b11000011100111001010 ?
b11011110100110100 =
b10100000011000010100 <
1:
b11101101111011001 9
b10100111100100110000 8
b100 '
b10100000011000010100 &
1#
b11101101111011001 "
b10100111100100110000 !
#40
b10111010001011101001 N
b10001001110101010111 K
b10100111100 H
b1000111100001110100 E
b1010001111000011101 B
b1000111100001110101 @
b10111111101111111001 >
b11001110101111100000 ;
b10100111100100110000 7
b0 2
1$
b11001101000111001011 %
b11101101111011001 M
b10100111100100110000 L
b11101101111011001 J
b10100111100100110000 I
b1001 G
b10100111100100110000 F
b10100011110000111010 C
b10100011110000111010 A
b10100011110000111010 ?
b11101101111011001 =
b10100111100100110000 <
b11001110101111100000 9
b11111110010111101010 8
b1001 '
b10100111100100110000 &
b11001110101111100000 "
b11111110010111101010 !
#50
b10010111000010001111 N
b1101010111101111011 K
b110100101 H
b110000101000000 E
b1010000001100001010 B
b1000000110000101001 @
b11111111010111101111 >
b1110111001000000100 ;
b1101001010101100101 *
b0 7
0$
b10000101000011100111 %
b11111110010111101010 M
b1101001010101100101 L
b11111110010111101010 J
b1101001010101100101 I
b1010 G
b1101001010101100101 F
b100 D
b10100000011000010100 C
b10100000011000010100 A
b10100000011000010100 ?
b11111110010111101010 =
b1101001010101100101 <
0:
b1101111011100011 9
b1110111001000000100 8
b1010 '
b1101001010101100101 &
0#
b1101111011100011 "
b1110111001000000100 !
#60
b101010111011100111 N
b11101010011011011001 K
b1100111010111 H
b11011110100110100000 E
b1101111010011010 B
b110111101001101000 @
b11101110111111100111 >
b111001010000111 ;
b11001110101111100000 5
b0 *
b101101110010010001 %
b11100100010100000111 M
b11001110101111100000 L
b11100100010100000111 J
b11001110101111100000 I
b111 G
b11001110101111100000 F
b11 D
b11011110100110100 C
b11011110100110100 A
b11011110100110100 ?
b11100100010100000111 =
b11001110101111100000 <
b100110101000001010 9
b111001010000111 8
b111 '
b11001110101111100000 &
b100110101000001010 "
b111001010000111 !
#70
b1111010110011100111 N
b1101001001100100001 K
b1110111001000000 H
b11110010011000000000 E
b1010011110010011000 B
b1001111001001100001 @
b1111111111011100111 >
b11110010010010011010 ;
b1110111001000000100 1
b0 5
1$
b11011111001110101101 %
b1101111011100011 M
b1110111001000000100 L
b1101111011100011 J
b1110111001000000100 I
b11 G
b1110111001000000100 F
b101 D
b10100111100100110000 C
b10100111100100110000 A
b10100111100100110000 ?
b1101111011100011 =
b1110111001000000100 <
1:
b11110010010010011010 9
b11101100111100010010 8
b11 '
b1110111001000000100 &
1#
b11110010010010011010 "
b11101100111100010010 !
#80
b11000000010001110111 N
b11000000010001101001 K
b1100011101101 H
b11011011110110010000 E
b10001110110111101100 B
b111011011110110010 @
b11000111011011110111 >
b10000110111010111000 ;
b11000111011011110000 5
b0 1
0$
b10101100011011111101 %
b111001010000111 M
b11000111011011110000 L
b111001010000111 J
b11000111011011110000 I
b111 G
b11000111011011110000 F
b100 D
b11101101111011001 C
b11101101111011001 A
b11101101111011001 ?
b111001010000111 =
b11000111011011110000 <
0:
b100101100001000101 9
b10000110111010111000 8
b111 '
b11000111011011110000 &
0#
b100101100001000101 "
b10000110111010111000 !
#90
b1110110100001001110 N
b11010110011111000110 K
b10011010100000 H
b101010110010100000 E
b10110100101010110010 B
b11010010101011001010 @
b1110110101001001110 >
b11101111110011011000 ;
b100110101000001010 2
b0 5
1$
b11101001100110111100 %
b1010000001001000100 M
b100110101000001010 L
b1010000001001000100 J
b100110101000001010 I
b100 G
b100110101000001010 F
b101 D
b1101001010101100101 C
b1101001010101100101 A
b1101001010101100101 ?
b1010000001001000100 =
b100110101000001010 <
1:
b11101111110011011000 9
b11111001110011100011 8
b100 '
b100110101000001010 &
1#
b11101111110011011000 "
b11111001110011100011 !
#100
b11110101110001000 N
b11111010101001111000 K
b1110110011 H
b11001011110101000000 E
b1111111001011110101 B
b11111100101111010101 @
b11111110111110011010 >
b110010110000011001 ;
b11101100111100010010 *
b0 2
0$
b1001110011100111000 %
b11110010010010011010 M
b11101100111100010010 L
b11110010010010011010 J
b11101100111100010010 I
b1010 G
b11101100111100010010 F
b11111110010111101010 C
b11111110010111101010 A
b11111110010111101010 ?
b11110010010010011010 =
b11101100111100010010 <
b110010110000011001 9
b11011101100011110 8
b1010 '
b11101100111100010010 &
b110010110000011001 "
b11011101100011110 !
#110
b10000000101101001011 6
b0 *
b1000 '
b10000000101101001011 &
#120
b100101100001000101 *
b0 6
b1010 '
b100101100001000101 &
#130
b11111001110011100011 6
b0 *
b1000 '
b11111001110011100011 &
#140
b10100100010100101101 .
b0 6
b1110 '
b10100100010100101101 &
#150
b110010110000011001 5
b0 .
b111 '
b110010110000011001 &
#160
b10100111111010111111 /
b0 5
b1111 '
b10100111111010111111 &
#170
b10111000100100011111 ,
b0 /
b1100 '
b10111000100100011111 &
#180
b111010111011000010 5
b0 ,
b111 '
b111010111011000010 &
#190
b11000011101111010111 4
b0 5
b110 '
b11000011101111010111 &
#200
b11110100010011011000 5
b0 4
b111 '
b11110100010011011000 &
#210
b11111001000000101000 ,
b0 5
b1100 '
b11111001000000101000 &
#220
b10110110110110000111 .
b0 ,
b1110 '
b10110110110110000111 &
#230
b101001010100000100 7
b0 .
b1001 '
b101001010100000100 &
#240
b1110001000000000010 ,
b0 7
b1100 '
b1110001000000000010 &
#250
b10001001010110001 4
b0 ,
b110 '
b10001001010110001 &
